synapticflow/__init__.py
synapticflow/decision/__init__.py
synapticflow/decision/decision.py
synapticflow/encoding/__init__.py
synapticflow/encoding/encoders.py
synapticflow/learning/__init__.py
synapticflow/learning/learning_rules.py
synapticflow/learning/rewards.py
synapticflow/network/__init__.py
synapticflow/network/connections.py
synapticflow/network/monitors.py
synapticflow/network/network.py
synapticflow/network/neural_populations.py
synapticflow/plotting/__init__.py
synapticflow/plotting/plotting.py
synapticflow/plotting/visualization.py
synapticflow/synapticflow.py
synapticflow/utils.py
synapticflow-0.0.7.dist-info/LICENSE
synapticflow-0.0.7.dist-info/METADATA
synapticflow-0.0.7.dist-info/WHEEL
synapticflow-0.0.7.dist-info/RECORD
