Metadata-Version: 2.1
Name: synapticflow
Version: 0.0.7
Summary: A powerful Python package for simulating spiking neural networks (SNNs) using PyTorch with GPU acceleration.
Keywords: Delay Learning,RSTDP,STDP,Spiking Neural Network (SNN)
Author: Arsham Gholamzadeh Khoee
Author-email: arsham.gh97@gmail.com
Maintainer: Arsham Gholamzadeh Khoee
Maintainer-email: arsham.gh97@gmail.com
Classifier: License :: OSI Approved :: MIT License
Classifier: Operating System :: OS Independent
Classifier: Programming Language :: Python :: 2
Classifier: Programming Language :: Python :: 2.7
Classifier: Programming Language :: Python :: 3
Classifier: Programming Language :: Python :: 3.4
Classifier: Programming Language :: Python :: 3.5
Classifier: Programming Language :: Python :: 3.6
Classifier: Programming Language :: Python :: 3.7
Classifier: Programming Language :: Python :: 3.8
Classifier: Programming Language :: Python :: 3.9
Classifier: Programming Language :: Python :: 3.10
Classifier: Programming Language :: Python :: 3.11
Requires-Dist: torch (<=1.13.1)
